imppkg/__init__.py
imppkg/hello.py
tejaspakcagelib-0.0.1.dist-info/LICENSE
tejaspakcagelib-0.0.1.dist-info/METADATA
tejaspakcagelib-0.0.1.dist-info/WHEEL
tejaspakcagelib-0.0.1.dist-info/top_level.txt
tejaspakcagelib-0.0.1.dist-info/RECORD
