Metadata-Version: 2.1
Name: tejaspakcagelib
Version: 0.0.1
Summary: this package does amazing things
Author: Tejas patil
Author-email: tejas9patil@gmail.com
License: MIT
Classifier: License :: OSI Approved :: MIT License
License-File: LICENSE
